test_user/__init__.py
test_user/apps.py
test_user/migrations/0001_initail.py
test_user/migrations/__init__.py
django_testuser-0.8.0.dist-info/METADATA
django_testuser-0.8.0.dist-info/WHEEL
django_testuser-0.8.0.dist-info/top_level.txt
django_testuser-0.8.0.dist-info/RECORD
