Metadata-Version: 2.1
Name: django-testuser
Version: 0.8.0
Summary: A default admin test user for non-prod env through a custom migration
Requires-Dist: django (>=2.1)
Requires-Dist: django-env-settings (>=0.12.0)
